telerun/__init__.py
telerun-0.0.10.dist-info/WHEEL
telerun-0.0.10.dist-info/entry_points.txt
telerun-0.0.10.dist-info/METADATA
telerun-0.0.10.dist-info/RECORD
