Metadata-Version: 2.3
Name: telerun
Version: 0.0.10
Summary: Add your description here
Requires-Dist: certifi
Requires-Python: >=3.12
